aea_ledger_ethereum_hwi/__init__.py
aea_ledger_ethereum_hwi/account.py
aea_ledger_ethereum_hwi/bip32.py
aea_ledger_ethereum_hwi/exceptions.py
aea_ledger_ethereum_hwi/hwi.py
aea_ledger_ethereum_hwi/py.typed
open_aea_ledger_ethereum_hwi-2.0.8.dist-info/licenses/LICENSE
open_aea_ledger_ethereum_hwi-2.0.8.dist-info/METADATA
open_aea_ledger_ethereum_hwi-2.0.8.dist-info/WHEEL
open_aea_ledger_ethereum_hwi-2.0.8.dist-info/entry_points.txt
open_aea_ledger_ethereum_hwi-2.0.8.dist-info/top_level.txt
open_aea_ledger_ethereum_hwi-2.0.8.dist-info/RECORD
