Metadata-Version: 2.4
Name: open-aea-ledger-ethereum-hwi
Version: 2.0.8
Summary: Python package wrapping the public and private key cryptography and support for hardware wallet interactions.
Author: Valory AG
License: Apache-2.0
Classifier: Environment :: Console
Classifier: Environment :: Web Environment
Classifier: Development Status :: 5 - Production/Stable
Classifier: Intended Audience :: Developers
Classifier: License :: OSI Approved :: Apache Software License
Classifier: Natural Language :: English
Classifier: Operating System :: MacOS
Classifier: Operating System :: Microsoft
Classifier: Operating System :: Unix
Classifier: Programming Language :: Python :: 3.10
Classifier: Programming Language :: Python :: 3.11
Classifier: Topic :: Communications
Classifier: Topic :: Internet
Classifier: Topic :: Software Development
License-File: LICENSE
Requires-Dist: open-aea<3.0.0,>=2.0.0
Requires-Dist: web3<8,>=7.0.0
Requires-Dist: ipfshttpclient==0.8.0a2
Requires-Dist: eth-account<0.14.0,>=0.13.0
Requires-Dist: open-aea-ledger-ethereum~=2.0.8
Requires-Dist: ledgerwallet==0.1.3
Requires-Dist: protobuf<4.25.0,>=4.21.6
Requires-Dist: construct<=2.10.61
Dynamic: author
Dynamic: classifier
Dynamic: description
Dynamic: description-content-type
Dynamic: license
Dynamic: license-file
Dynamic: requires-dist
Dynamic: summary
